README
nose_order_plugin.py
setup.cfg
setup.py
nose_order_plugin.egg-info/PKG-INFO
nose_order_plugin.egg-info/SOURCES.txt
nose_order_plugin.egg-info/dependency_links.txt
nose_order_plugin.egg-info/entry_points.txt
nose_order_plugin.egg-info/not-zip-safe
nose_order_plugin.egg-info/requires.txt
nose_order_plugin.egg-info/top_level.txt