Metadata-Version: 1.0
Name: nose-order-plugin
Version: 0.1
Summary: Nose test method ordering plugin
Home-page: http://github.com/encukou/nose_order_plugin
Author: Petr Viktorin
Author-email: encukou@gmail.com
License: GNU GPLv3+
Platform: UNKNOWN
